ltapysg/__init__.py
ltapysg/api.py
ltapysg/bus.py
ltapysg/exceptions.py
ltapysg/taxi.py
ltapysg/traffic.py
ltapysg-0.1.5.dist-info/LICENSE
ltapysg-0.1.5.dist-info/METADATA
ltapysg-0.1.5.dist-info/WHEEL
ltapysg-0.1.5.dist-info/top_level.txt
ltapysg-0.1.5.dist-info/RECORD
